{"from": "Ciudad Neily", "monday": [{"date_arr": "Mo, 12/23", "date_dep": "Mo, 12/23", "from": "Ciudad Neily", "from_lat": "8.64885800571874", "from_link": "http://horariodebuses.com/cr/busstop.php?city=Ciudad%20Neily&lang=en&ruta=bu,f&comp=Transportes%20Terraba&tele=2783-4293&cweb=www.terrabasur.net&ort=Mercado%20&lon=-82.9418635368347&lat=8.64885800571874", "from_lon": "82.9418635368347", "remarks": " Journey duration: 1:20h Bus:  continues to Puerto Jiménez ", "time_arr": "08:20", "time_dep": "07:00", "to": "Mogos", "to_link": "http://horariodebuses.com/cr/busstop.php?city=Mogos&lang=en&ruta=bu,t&comp=Transportes%20Terraba&tele=2783-4293&cweb=www.terrabasur.net&ort=&lon=0&lat=0", "trans_link": "http://www.terrabasur.net", "trans_name": "Transportes Térraba", "trans_tel": "2783-4293"}, {"date_arr": "Mo, 12/23", "date_dep": "Mo, 12/23", "from": "Ciudad Neily", "from_lat": "8.64885800571874", "from_link": "http://horariodebuses.com/cr/busstop.php?city=Ciudad%20Neily&lang=en&ruta=bu,f&comp=Transportes%20Terraba&tele=2783-4293&cweb=www.terrabasur.net&ort=Mercado%20&lon=-82.9418635368347&lat=8.64885800571874", "from_lon": "82.9418635368347", "remarks": " Journey duration: 1:20h Bus:  continues to Puerto Jiménez ", "time_arr": "15:20", "time_dep": "14:00", "to": "Mogos", "to_link": "http://horariodebuses.com/cr/busstop.php?city=Mogos&lang=en&ruta=bu,t&comp=Transportes%20Terraba&tele=2783-4293&cweb=www.terrabasur.net&ort=&lon=0&lat=0", "trans_link": "http://www.terrabasur.net", "trans_name": "Transportes Térraba", "trans_tel": "2783-4293"}], "to": "Mogos", "tuesday": [{"date_arr": "Tu, 12/24", "date_dep": "Tu, 12/24", "from": "Ciudad Neily", "from_lat": "8.64885800571874", "from_link": "http://horariodebuses.com/cr/busstop.php?city=Ciudad%20Neily&lang=en&ruta=bu,f&comp=Transportes%20Terraba&tele=2783-4293&cweb=www.terrabasur.net&ort=Mercado%20&lon=-82.9418635368347&lat=8.64885800571874", "from_lon": "82.9418635368347", "remarks": " Journey duration: 1:20h Bus:  continues to Puerto Jiménez ", "time_arr": "08:20", "time_dep": "07:00", "to": "Mogos", "to_link": "http://horariodebuses.com/cr/busstop.php?city=Mogos&lang=en&ruta=bu,t&comp=Transportes%20Terraba&tele=2783-4293&cweb=www.terrabasur.net&ort=&lon=0&lat=0", "trans_link": "http://www.terrabasur.net", "trans_name": "Transportes Térraba", "trans_tel": "2783-4293"}, {"date_arr": "Tu, 12/24", "date_dep": "Tu, 12/24", "from": "Ciudad Neily", "from_lat": "8.64885800571874", "from_link": "http://horariodebuses.com/cr/busstop.php?city=Ciudad%20Neily&lang=en&ruta=bu,f&comp=Transportes%20Terraba&tele=2783-4293&cweb=www.terrabasur.net&ort=Mercado%20&lon=-82.9418635368347&lat=8.64885800571874", "from_lon": "82.9418635368347", "remarks": " Journey duration: 1:20h Bus:  continues to Puerto Jiménez ", "time_arr": "15:20", "time_dep": "14:00", "to": "Mogos", "to_link": "http://horariodebuses.com/cr/busstop.php?city=Mogos&lang=en&ruta=bu,t&comp=Transportes%20Terraba&tele=2783-4293&cweb=www.terrabasur.net&ort=&lon=0&lat=0", "trans_link": "http://www.terrabasur.net", "trans_name": "Transportes Térraba", "trans_tel": "2783-4293"}], "wednesday": [{"date_arr": "We, 12/25", "date_dep": "We, 12/25", "from": "Ciudad Neily", "from_lat": "8.64885800571874", "from_link": "http://horariodebuses.com/cr/busstop.php?city=Ciudad%20Neily&lang=en&ruta=bu,f&comp=Transportes%20Terraba&tele=2783-4293&cweb=www.terrabasur.net&ort=Mercado%20&lon=-82.9418635368347&lat=8.64885800571874", "from_lon": "82.9418635368347", "remarks": " Journey duration: 1:20h Bus:  continues to Puerto Jiménez ", "time_arr": "08:20", "time_dep": "07:00", "to": "Mogos", "to_link": "http://horariodebuses.com/cr/busstop.php?city=Mogos&lang=en&ruta=bu,t&comp=Transportes%20Terraba&tele=2783-4293&cweb=www.terrabasur.net&ort=&lon=0&lat=0", "trans_link": "http://www.terrabasur.net", "trans_name": "Transportes Térraba", "trans_tel": "2783-4293"}, {"date_arr": "We, 12/25", "date_dep": "We, 12/25", "from": "Ciudad Neily", "from_lat": "8.64885800571874", "from_link": "http://horariodebuses.com/cr/busstop.php?city=Ciudad%20Neily&lang=en&ruta=bu,f&comp=Transportes%20Terraba&tele=2783-4293&cweb=www.terrabasur.net&ort=Mercado%20&lon=-82.9418635368347&lat=8.64885800571874", "from_lon": "82.9418635368347", "remarks": " Journey duration: 1:20h Bus:  continues to Puerto Jiménez ", "time_arr": "15:20", "time_dep": "14:00", "to": "Mogos", "to_link": "http://horariodebuses.com/cr/busstop.php?city=Mogos&lang=en&ruta=bu,t&comp=Transportes%20Terraba&tele=2783-4293&cweb=www.terrabasur.net&ort=&lon=0&lat=0", "trans_link": "http://www.terrabasur.net", "trans_name": "Transportes Térraba", "trans_tel": "2783-4293"}]}