{"91.57919173850442": {"lat": 8.63732820166971, "lon": 82.9418635368347, "schedule": {"monday": [{"date_arr": "monday", "remarks": " Journey duration: 4:00h Bus ", "time_arr": "08:30", "time_dep": "04:30", "to_lat": "9.37353666657766", "to_lon": "83.7016421556473", "trans_link": "http://www.tracopacr.com", "trans_name": "Tracopa", "trans_tel": "2258-8939"}, {"date_arr": "monday", "remarks": " Journey duration: 4:00h Bus ", "time_arr": "12:00", "time_dep": "08:00", "to_lat": "9.37353666657766", "to_lon": "83.7016421556473", "trans_link": "http://www.tracopacr.com", "trans_name": "Tracopa", "trans_tel": "2258-8939"}, {"date_arr": "monday", "remarks": " Journey duration: 4:00h Bus ", "time_arr": "21:00", "time_dep": "17:00", "to_lat": "9.37353666657766", "to_lon": "83.7016421556473", "trans_link": "http://www.tracopacr.com", "trans_name": "Tracopa", "trans_tel": "2258-8939"}], "tuesday": [{"date_arr": "tuesday", "remarks": " Journey duration: 4:00h Bus ", "time_arr": "08:30", "time_dep": "04:30", "to_lat": "9.37353666657766", "to_lon": "83.7016421556473", "trans_link": "http://www.tracopacr.com", "trans_name": "Tracopa", "trans_tel": "2258-8939"}, {"date_arr": "tuesday", "remarks": " Journey duration: 4:00h Bus ", "time_arr": "12:00", "time_dep": "08:00", "to_lat": "9.37353666657766", "to_lon": "83.7016421556473", "trans_link": "http://www.tracopacr.com", "trans_name": "Tracopa", "trans_tel": "2258-8939"}, {"date_arr": "tuesday", "remarks": " Journey duration: 4:00h Bus ", "time_arr": "21:00", "time_dep": "17:00", "to_lat": "9.37353666657766", "to_lon": "83.7016421556473", "trans_link": "http://www.tracopacr.com", "trans_name": "Tracopa", "trans_tel": "2258-8939"}], "wednesday": [{"date_arr": "wednesday", "remarks": " Journey duration: 4:00h Bus ", "time_arr": "08:30", "time_dep": "04:30", "to_lat": "9.37353666657766", "to_lon": "83.7016421556473", "trans_link": "http://www.tracopacr.com", "trans_name": "Tracopa", "trans_tel": "2258-8939"}, {"date_arr": "wednesday", "remarks": " Journey duration: 4:00h Bus ", "time_arr": "12:00", "time_dep": "08:00", "to_lat": "9.37353666657766", "to_lon": "83.7016421556473", "trans_link": "http://www.tracopacr.com", "trans_name": "Tracopa", "trans_tel": "2258-8939"}]}}, "91.59072154255344": {"lat": 8.64885800571874, "lon": 82.9418635368347, "schedule": {"monday": [{"date_arr": "monday", "remarks": " Journey duration: 4:00h Bus:  comes from Paso Canoas ", "time_arr": "08:00", "time_dep": "04:00", "to_lat": "9.37353666657766", "to_lon": "83.7016421556473", "trans_link": "http://www.tracopacr.com", "trans_name": "Tracopa", "trans_tel": "2221-4214"}, {"date_arr": "monday", "remarks": " Journey duration: 4:00h Bus:  comes from Laurel ", "time_arr": "08:00", "time_dep": "04:00", "to_lat": "9.37353666657766", "to_lon": "83.7016421556473", "trans_link": "http://www.tracopacr.com", "trans_name": "Tracopa", "trans_tel": "2221-4214"}, {"date_arr": "monday", "remarks": " Journey duration: 4:00h Bus:  comes from Coto 47 ", "time_arr": "08:50", "time_dep": "04:50", "trans_link": "http://www.tracopacr.com", "trans_name": "Tracopa", "trans_tel": "2221-4214"}, {"date_arr": "monday", "remarks": " Journey duration: 4:00h Bus ", "time_arr": "11:00", "time_dep": "07:00", "to_lat": "9.37298092322521", "to_lon": "83.7017440795898", "trans_link": "http://www.tracopacr.com", "trans_name": "Tracopa", "trans_tel": "2221-4214"}, {"date_arr": "monday", "remarks": " Journey duration: 4:00h Bus:  comes from Paso Canoas ", "time_arr": "12:30", "time_dep": "08:30", "to_lat": "9.37353666657766", "to_lon": "83.7016421556473", "trans_link": "http://www.tracopacr.com", "trans_name": "Tracopa", "trans_tel": "2221-4214"}, {"date_arr": "monday", "remarks": " Journey duration: 4:00h Bus ", "time_arr": "14:30", "time_dep": "10:30", "to_lat": "9.37298092322521", "to_lon": "83.7017440795898", "trans_link": "http://www.tracopacr.com", "trans_name": "Tracopa", "trans_tel": "2221-4214"}, {"date_arr": "monday", "remarks": " Journey duration: 4:00h Bus:  comes from Paso Canoas ", "time_arr": "15:30", "time_dep": "11:30", "to_lat": "9.37353666657766", "to_lon": "83.7016421556473", "trans_link": "http://www.tracopacr.com", "trans_name": "Tracopa", "trans_tel": "2221-4214"}, {"date_arr": "monday", "remarks": " Journey duration: 4:00h Bus ", "time_arr": "17:15", "time_dep": "13:15", "to_lat": "9.37298092322521", "to_lon": "83.7017440795898", "trans_link": "http://www.tracopacr.com", "trans_name": "Tracopa", "trans_tel": "2221-4214"}, {"date_arr": "monday", "remarks": " Journey duration: 4:00h Bus ", "time_arr": "19:30", "time_dep": "15:30", "to_lat": "9.37298092322521", "to_lon": "83.7017440795898", "trans_link": "http://www.tracopacr.com", "trans_name": "Tracopa", "trans_tel": "2221-4214"}, {"date_arr": "monday", "remarks": " Journey duration: 4:00h Bus:  comes from Paso Canoas ", "time_arr": "21:00", "time_dep": "17:00", "to_lat": "9.37353666657766", "to_lon": "83.7016421556473", "trans_link": "http://www.tracopacr.com", "trans_name": "Tracopa", "trans_tel": "2221-4214"}], "tuesday": [{"date_arr": "tuesday", "remarks": " Journey duration: 4:00h Bus:  comes from Paso Canoas ", "time_arr": "08:00", "time_dep": "04:00", "to_lat": "9.37353666657766", "to_lon": "83.7016421556473", "trans_link": "http://www.tracopacr.com", "trans_name": "Tracopa", "trans_tel": "2221-4214"}, {"date_arr": "tuesday", "remarks": " Journey duration: 4:00h Bus:  comes from Laurel ", "time_arr": "08:00", "time_dep": "04:00", "to_lat": "9.37353666657766", "to_lon": "83.7016421556473", "trans_link": "http://www.tracopacr.com", "trans_name": "Tracopa", "trans_tel": "2221-4214"}, {"date_arr": "tuesday", "remarks": " Journey duration: 4:00h Bus:  comes from Coto 47 ", "time_arr": "08:50", "time_dep": "04:50", "trans_link": "http://www.tracopacr.com", "trans_name": "Tracopa", "trans_tel": "2221-4214"}, {"date_arr": "tuesday", "remarks": " Journey duration: 4:00h Bus ", "time_arr": "11:00", "time_dep": "07:00", "to_lat": "9.37298092322521", "to_lon": "83.7017440795898", "trans_link": "http://www.tracopacr.com", "trans_name": "Tracopa", "trans_tel": "2221-4214"}, {"date_arr": "tuesday", "remarks": " Journey duration: 4:00h Bus:  comes from Paso Canoas ", "time_arr": "12:30", "time_dep": "08:30", "to_lat": "9.37353666657766", "to_lon": "83.7016421556473", "trans_link": "http://www.tracopacr.com", "trans_name": "Tracopa", "trans_tel": "2221-4214"}, {"date_arr": "tuesday", "remarks": " Journey duration: 4:00h Bus ", "time_arr": "14:30", "time_dep": "10:30", "to_lat": "9.37298092322521", "to_lon": "83.7017440795898", "trans_link": "http://www.tracopacr.com", "trans_name": "Tracopa", "trans_tel": "2221-4214"}, {"date_arr": "tuesday", "remarks": " Journey duration: 4:00h Bus:  comes from Paso Canoas ", "time_arr": "15:30", "time_dep": "11:30", "to_lat": "9.37353666657766", "to_lon": "83.7016421556473", "trans_link": "http://www.tracopacr.com", "trans_name": "Tracopa", "trans_tel": "2221-4214"}, {"date_arr": "tuesday", "remarks": " Journey duration: 4:00h Bus ", "time_arr": "17:15", "time_dep": "13:15", "to_lat": "9.37298092322521", "to_lon": "83.7017440795898", "trans_link": "http://www.tracopacr.com", "trans_name": "Tracopa", "trans_tel": "2221-4214"}, {"date_arr": "tuesday", "remarks": " Journey duration: 4:00h Bus ", "time_arr": "19:30", "time_dep": "15:30", "to_lat": "9.37298092322521", "to_lon": "83.7017440795898", "trans_link": "http://www.tracopacr.com", "trans_name": "Tracopa", "trans_tel": "2221-4214"}, {"date_arr": "tuesday", "remarks": " Journey duration: 4:00h Bus:  comes from Paso Canoas ", "time_arr": "21:00", "time_dep": "17:00", "to_lat": "9.37353666657766", "to_lon": "83.7016421556473", "trans_link": "http://www.tracopacr.com", "trans_name": "Tracopa", "trans_tel": "2221-4214"}], "wednesday": [{"date_arr": "wednesday", "remarks": " Journey duration: 4:00h Bus:  comes from Paso Canoas ", "time_arr": "08:00", "time_dep": "04:00", "to_lat": "9.37353666657766", "to_lon": "83.7016421556473", "trans_link": "http://www.tracopacr.com", "trans_name": "Tracopa", "trans_tel": "2221-4214"}, {"date_arr": "wednesday", "remarks": " Journey duration: 4:00h Bus:  comes from Laurel ", "time_arr": "08:00", "time_dep": "04:00", "to_lat": "9.37353666657766", "to_lon": "83.7016421556473", "trans_link": "http://www.tracopacr.com", "trans_name": "Tracopa", "trans_tel": "2221-4214"}, {"date_arr": "wednesday", "remarks": " Journey duration: 4:00h Bus:  comes from Coto 47 ", "time_arr": "08:50", "time_dep": "04:50", "trans_link": "http://www.tracopacr.com", "trans_name": "Tracopa", "trans_tel": "2221-4214"}, {"date_arr": "wednesday", "remarks": " Journey duration: 4:00h Bus ", "time_arr": "11:00", "time_dep": "07:00", "to_lat": "9.37298092322521", "to_lon": "83.7017440795898", "trans_link": "http://www.tracopacr.com", "trans_name": "Tracopa", "trans_tel": "2221-4214"}, {"date_arr": "wednesday", "remarks": " Journey duration: 4:00h Bus:  comes from Paso Canoas ", "time_arr": "12:30", "time_dep": "08:30", "to_lat": "9.37353666657766", "to_lon": "83.7016421556473", "trans_link": "http://www.tracopacr.com", "trans_name": "Tracopa", "trans_tel": "2221-4214"}, {"date_arr": "wednesday", "remarks": " Journey duration: 4:00h Bus ", "time_arr": "14:30", "time_dep": "10:30", "to_lat": "9.37298092322521", "to_lon": "83.7017440795898", "trans_link": "http://www.tracopacr.com", "trans_name": "Tracopa", "trans_tel": "2221-4214"}]}}}