{"friday": [{"date_arr": "Fr, 12/27", "date_dep": "Fr, 12/27", "from": "Barranca", "from_link": "http://horariodebuses.com/cr/busstop.php?city=Barranca&lang=en&ruta=bu,f&comp=Transnorte%20de%20Upala&tele=2221-3318&cweb=&ort=%20&lon=0&lat=0", "remarks": " Journey duration: 2:30h Bus ", "time_arr": "10:30", "time_dep": "08:00", "to": "Aguas Claras", "to_link": "http://horariodebuses.com/cr/busstop.php?city=Aguas%20Claras&lang=en&ruta=bu,t&comp=Transnorte%20de%20Upala&tele=2221-3318&cweb=&ort=&lon=0&lat=0", "trans_name": "Transnorte de Upala", "trans_tel": "2221-3318"}, {"date_arr": "Fr, 12/27", "date_dep": "Fr, 12/27", "from": "Barranca", "from_link": "http://horariodebuses.com/cr/busstop.php?city=Barranca&lang=en&ruta=bu,f&comp=Transnorte%20de%20Upala&tele=2221-3318&cweb=&ort=%20&lon=0&lat=0", "remarks": " Journey duration: 2:30h Bus ", "time_arr": "19:00", "time_dep": "16:30", "to": "Aguas Claras", "to_link": "http://horariodebuses.com/cr/busstop.php?city=Aguas%20Claras&lang=en&ruta=bu,t&comp=Transnorte%20de%20Upala&tele=2221-3318&cweb=&ort=&lon=0&lat=0", "trans_name": "Transnorte de Upala", "trans_tel": "2221-3318"}], "from": "Barranca", "monday": [{"date_arr": "Mo, 12/23", "date_dep": "Mo, 12/23", "from": "Barranca", "from_link": "http://horariodebuses.com/cr/busstop.php?city=Barranca&lang=en&ruta=bu,f&comp=Transnorte%20de%20Upala&tele=2221-3318&cweb=&ort=%20&lon=0&lat=0", "remarks": " Journey duration: 2:30h Bus ", "time_arr": "10:30", "time_dep": "08:00", "to": "Aguas Claras", "to_link": "http://horariodebuses.com/cr/busstop.php?city=Aguas%20Claras&lang=en&ruta=bu,t&comp=Transnorte%20de%20Upala&tele=2221-3318&cweb=&ort=&lon=0&lat=0", "trans_name": "Transnorte de Upala", "trans_tel": "2221-3318"}, {"date_arr": "Mo, 12/23", "date_dep": "Mo, 12/23", "from": "Barranca", "from_link": "http://horariodebuses.com/cr/busstop.php?city=Barranca&lang=en&ruta=bu,f&comp=Transnorte%20de%20Upala&tele=2221-3318&cweb=&ort=%20&lon=0&lat=0", "remarks": " Journey duration: 2:30h Bus ", "time_arr": "19:00", "time_dep": "16:30", "to": "Aguas Claras", "to_link": "http://horariodebuses.com/cr/busstop.php?city=Aguas%20Claras&lang=en&ruta=bu,t&comp=Transnorte%20de%20Upala&tele=2221-3318&cweb=&ort=&lon=0&lat=0", "trans_name": "Transnorte de Upala", "trans_tel": "2221-3318"}], "saturday": [{"date_arr": "Sa, 12/28", "date_dep": "Sa, 12/28", "from": "Barranca", "from_link": "http://horariodebuses.com/cr/busstop.php?city=Barranca&lang=en&ruta=bu,f&comp=Transnorte%20de%20Upala&tele=2221-3318&cweb=&ort=%20&lon=0&lat=0", "remarks": " Journey duration: 2:30h Bus ", "time_arr": "10:30", "time_dep": "08:00", "to": "Aguas Claras", "to_link": "http://horariodebuses.com/cr/busstop.php?city=Aguas%20Claras&lang=en&ruta=bu,t&comp=Transnorte%20de%20Upala&tele=2221-3318&cweb=&ort=&lon=0&lat=0", "trans_name": "Transnorte de Upala", "trans_tel": "2221-3318"}, {"date_arr": "Sa, 12/28", "date_dep": "Sa, 12/28", "from": "Barranca", "from_link": "http://horariodebuses.com/cr/busstop.php?city=Barranca&lang=en&ruta=bu,f&comp=Transnorte%20de%20Upala&tele=2221-3318&cweb=&ort=%20&lon=0&lat=0", "remarks": " Journey duration: 2:30h Bus ", "time_arr": "19:00", "time_dep": "16:30", "to": "Aguas Claras", "to_link": "http://horariodebuses.com/cr/busstop.php?city=Aguas%20Claras&lang=en&ruta=bu,t&comp=Transnorte%20de%20Upala&tele=2221-3318&cweb=&ort=&lon=0&lat=0", "trans_name": "Transnorte de Upala", "trans_tel": "2221-3318"}], "sunday": [{"date_arr": "Su, 12/29", "date_dep": "Su, 12/29", "from": "Barranca", "from_link": "http://horariodebuses.com/cr/busstop.php?city=Barranca&lang=en&ruta=bu,f&comp=Transnorte%20de%20Upala&tele=2221-3318&cweb=&ort=%20&lon=0&lat=0", "remarks": " Journey duration: 2:30h Bus ", "time_arr": "10:30", "time_dep": "08:00", "to": "Aguas Claras", "to_link": "http://horariodebuses.com/cr/busstop.php?city=Aguas%20Claras&lang=en&ruta=bu,t&comp=Transnorte%20de%20Upala&tele=2221-3318&cweb=&ort=&lon=0&lat=0", "trans_name": "Transnorte de Upala", "trans_tel": "2221-3318"}, {"date_arr": "Su, 12/29", "date_dep": "Su, 12/29", "from": "Barranca", "from_link": "http://horariodebuses.com/cr/busstop.php?city=Barranca&lang=en&ruta=bu,f&comp=Transnorte%20de%20Upala&tele=2221-3318&cweb=&ort=%20&lon=0&lat=0", "remarks": " Journey duration: 2:30h Bus ", "time_arr": "19:00", "time_dep": "16:30", "to": "Aguas Claras", "to_link": "http://horariodebuses.com/cr/busstop.php?city=Aguas%20Claras&lang=en&ruta=bu,t&comp=Transnorte%20de%20Upala&tele=2221-3318&cweb=&ort=&lon=0&lat=0", "trans_name": "Transnorte de Upala", "trans_tel": "2221-3318"}], "thursday": [{"date_arr": "Th, 12/26", "date_dep": "Th, 12/26", "from": "Barranca", "from_link": "http://horariodebuses.com/cr/busstop.php?city=Barranca&lang=en&ruta=bu,f&comp=Transnorte%20de%20Upala&tele=2221-3318&cweb=&ort=%20&lon=0&lat=0", "remarks": " Journey duration: 2:30h Bus ", "time_arr": "10:30", "time_dep": "08:00", "to": "Aguas Claras", "to_link": "http://horariodebuses.com/cr/busstop.php?city=Aguas%20Claras&lang=en&ruta=bu,t&comp=Transnorte%20de%20Upala&tele=2221-3318&cweb=&ort=&lon=0&lat=0", "trans_name": "Transnorte de Upala", "trans_tel": "2221-3318"}, {"date_arr": "Th, 12/26", "date_dep": "Th, 12/26", "from": "Barranca", "from_link": "http://horariodebuses.com/cr/busstop.php?city=Barranca&lang=en&ruta=bu,f&comp=Transnorte%20de%20Upala&tele=2221-3318&cweb=&ort=%20&lon=0&lat=0", "remarks": " Journey duration: 2:30h Bus ", "time_arr": "19:00", "time_dep": "16:30", "to": "Aguas Claras", "to_link": "http://horariodebuses.com/cr/busstop.php?city=Aguas%20Claras&lang=en&ruta=bu,t&comp=Transnorte%20de%20Upala&tele=2221-3318&cweb=&ort=&lon=0&lat=0", "trans_name": "Transnorte de Upala", "trans_tel": "2221-3318"}], "to": "Aguas Claras", "tuesday": [{"date_arr": "Tu, 12/24", "date_dep": "Tu, 12/24", "from": "Barranca", "from_link": "http://horariodebuses.com/cr/busstop.php?city=Barranca&lang=en&ruta=bu,f&comp=Transnorte%20de%20Upala&tele=2221-3318&cweb=&ort=%20&lon=0&lat=0", "remarks": " Journey duration: 2:30h Bus ", "time_arr": "10:30", "time_dep": "08:00", "to": "Aguas Claras", "to_link": "http://horariodebuses.com/cr/busstop.php?city=Aguas%20Claras&lang=en&ruta=bu,t&comp=Transnorte%20de%20Upala&tele=2221-3318&cweb=&ort=&lon=0&lat=0", "trans_name": "Transnorte de Upala", "trans_tel": "2221-3318"}, {"date_arr": "Tu, 12/24", "date_dep": "Tu, 12/24", "from": "Barranca", "from_link": "http://horariodebuses.com/cr/busstop.php?city=Barranca&lang=en&ruta=bu,f&comp=Transnorte%20de%20Upala&tele=2221-3318&cweb=&ort=%20&lon=0&lat=0", "remarks": " Journey duration: 2:30h Bus ", "time_arr": "19:00", "time_dep": "16:30", "to": "Aguas Claras", "to_link": "http://horariodebuses.com/cr/busstop.php?city=Aguas%20Claras&lang=en&ruta=bu,t&comp=Transnorte%20de%20Upala&tele=2221-3318&cweb=&ort=&lon=0&lat=0", "trans_name": "Transnorte de Upala", "trans_tel": "2221-3318"}], "wednesday": [{"date_arr": "We, 12/25", "date_dep": "We, 12/25", "from": "Barranca", "from_link": "http://horariodebuses.com/cr/busstop.php?city=Barranca&lang=en&ruta=bu,f&comp=Transnorte%20de%20Upala&tele=2221-3318&cweb=&ort=%20&lon=0&lat=0", "remarks": " Journey duration: 2:30h Bus ", "time_arr": "10:30", "time_dep": "08:00", "to": "Aguas Claras", "to_link": "http://horariodebuses.com/cr/busstop.php?city=Aguas%20Claras&lang=en&ruta=bu,t&comp=Transnorte%20de%20Upala&tele=2221-3318&cweb=&ort=&lon=0&lat=0", "trans_name": "Transnorte de Upala", "trans_tel": "2221-3318"}, {"date_arr": "We, 12/25", "date_dep": "We, 12/25", "from": "Barranca", "from_link": "http://horariodebuses.com/cr/busstop.php?city=Barranca&lang=en&ruta=bu,f&comp=Transnorte%20de%20Upala&tele=2221-3318&cweb=&ort=%20&lon=0&lat=0", "remarks": " Journey duration: 2:30h Bus ", "time_arr": "19:00", "time_dep": "16:30", "to": "Aguas Claras", "to_link": "http://horariodebuses.com/cr/busstop.php?city=Aguas%20Claras&lang=en&ruta=bu,t&comp=Transnorte%20de%20Upala&tele=2221-3318&cweb=&ort=&lon=0&lat=0", "trans_name": "Transnorte de Upala", "trans_tel": "2221-3318"}]}